gpbacay_arcane/__init__.py
gpbacay_arcane/callbacks.py
gpbacay_arcane/cli_commands.py
gpbacay_arcane/foundational_models.py
gpbacay_arcane/layers.py
gpbacay_arcane/mechanisms.py
gpbacay_arcane/models.py
gpbacay_arcane/ollama_integration.py
gpbacay_arcane-3.0.2.dist-info/licenses/LICENSE
gpbacay_arcane-3.0.2.dist-info/METADATA
gpbacay_arcane-3.0.2.dist-info/WHEEL
gpbacay_arcane-3.0.2.dist-info/entry_points.txt
gpbacay_arcane-3.0.2.dist-info/top_level.txt
gpbacay_arcane-3.0.2.dist-info/RECORD
