Metadata-Version: 2.4
Name: gpbacay-arcane
Version: 3.0.2
Summary: A neuromimetic semantic foundation model library with biologically-inspired neural mechanisms including spiking neural networks, Hebbian learning, and homeostatic plasticity
Home-page: https://github.com/gpbacay/gpbacay_arcane
Author: Gianne P. Bacay
Author-email: giannebacay2004@gmail.com
Project-URL: Bug Reports, https://github.com/gpbacay/gpbacay_arcane/issues
Project-URL: Source, https://github.com/gpbacay/gpbacay_arcane
Project-URL: Documentation, https://github.com/gpbacay/gpbacay_arcane#readme
Keywords: neuromimetic,neural-network,semantic-model,spiking-neural-network,hebbian-learning,reservoir-computing,tensorflow,deep-learning,computational-neuroscience
Classifier: Development Status :: 4 - Beta
Classifier: Intended Audience :: Developers
Classifier: Intended Audience :: Science/Research
Classifier: License :: OSI Approved :: MIT License
Classifier: Operating System :: OS Independent
Classifier: Programming Language :: Python :: 3
Classifier: Programming Language :: Python :: 3.8
Classifier: Programming Language :: Python :: 3.9
Classifier: Programming Language :: Python :: 3.10
Classifier: Programming Language :: Python :: 3.11
Classifier: Topic :: Scientific/Engineering :: Artificial Intelligence
Classifier: Topic :: Scientific/Engineering :: Bio-Informatics
Requires-Python: >=3.8
License-File: LICENSE
Requires-Dist: numpy>=1.21.0
Requires-Dist: tensorflow>=2.12.0
Requires-Dist: keras>=2.12.0
Requires-Dist: matplotlib>=3.5.0
Provides-Extra: ollama
Requires-Dist: ollama>=0.1.0; extra == "ollama"
Requires-Dist: sentence-transformers>=2.2.0; extra == "ollama"
Provides-Extra: dev
Requires-Dist: pytest>=7.0.0; extra == "dev"
Requires-Dist: black>=23.0.0; extra == "dev"
Requires-Dist: flake8>=6.0.0; extra == "dev"
Dynamic: author
Dynamic: author-email
Dynamic: classifier
Dynamic: description
Dynamic: description-content-type
Dynamic: home-page
Dynamic: keywords
Dynamic: license-file
Dynamic: project-url
Dynamic: provides-extra
Dynamic: requires-dist
Dynamic: requires-python
Dynamic: summary
